{
  "1.12.2": {
    "date": "2026-06-29",
    "changes": {
      "feature": ["新增 markdown-it-mark 插件，支持 <mark> / == 高亮标记语法"],
      "fix": [
        "修复脚注等样式在 Callout 及聊天容器内渲染失效的问题",
        "修复段评标题过滤与内容识别异常"
      ],
      "improve": ["调整并优化 Markdown 相关样式"]
    }
  },
  "1.12.1": {
    "date": "2026-06-28",
    "changes": {
      "fix": [
        "修复 Giscus 在网络不佳时加载失败的问题，并支持动态重载",
        "修复渲染插件 markdown-it-alert 对子元素进行两次解析的问题"
      ],
      "refactor": [
        "重构聊天和动态内容渲染插件（markdown-it-chat），优化代码结构与可读性",
        "优化段落评论的 ID 生成与状态管理"
      ],
      "improve": ["调整段落评论的按钮图标与交互样式"],
      "chore": ["更新网站图标", "清理废弃的 SVG 文件"]
    }
  },
  "1.12.0": {
    "date": "2026-06-28",
    "changes": {
      "feature": [
        "新增段评数量接口，支持从 GitHub Discussions 获取段落评论计数",
        "新增 Markdown 特性加载器，支持按需懒加载代码高亮语言，优化打包体积",
        "为 Giscus 评论引入 Manrope 字体，与主站字体样式统一"
      ],
      "fix": ["修复 Giscus 在博客页面创建新评论失效的问题"],
      "refactor": [
        "重构 Giscus 配置结构，新增主题映射、mappings 和 configs 分组，提升可维护性",
        "优化章节和位置跟踪逻辑，更新路由配置"
      ],
      "improve": ["调整代码块样式并添加段落评论计数样式"],
      "chore": ["整理组件目录结构（articles → blog/reader），提高可维护性"]
    }
  },
  "1.11.1": {
    "date": "2026-06-25",
    "changes": {
      "fix": ["修复文章数据获取与图片处理流程异常"]
    }
  },
  "1.11.0": {
    "date": "2026-06-24",
    "changes": {
      "feature": [
        "新增博客推文页面与文章列表/阅读组件，支持独立查看推文内容",
        "支持在段落评论中读取当前段落文本，提升评论定位体验"
      ],
      "fix": [
        "修正阅读器默认字体大小与行高，提升阅读体验",
        "修复触屏端代码块复制按钮和标题锚点无法触发的问题",
        "修复回到顶部按钮隐藏时仍可点击的问题"
      ],
      "improve": [
        "统一字体设置与整体排版样式，提升可读性和一致性",
        "调整组件样式以提升视觉层次和一致性",
        "优化侧边栏和子菜单组件的样式以提升布局一致性"
      ],
      "refactor": [
        "优化滚动容器获取和滚动逻辑以提升性能和可读性",
        "重组小说组件结构并更新相关引用",
        "重构浮动操作按钮组件以适配更多场景",
        "实现 GitHub Callout 类型与现有 alert 排版的映射和解析"
      ]
    }
  },
  "1.10.0": {
    "date": "2026-06-21",
    "changes": {
      "feature": [
        "新增 Giscus 自定义主题，四套配色分别适配 daisyUI 的 lemonade（默认日间）、forest（默认夜间）、corporate（日间模式）、dim（夜间模式）"
      ],
      "fix": ["修复段落关闭时隐藏的按钮渲染问题"],
      "improve": [
        "优化 Markdown 内容样式及排版（标题、段落、Alert 警告框、列表项）",
        "优化服务器地址提示信息及样式",
        "调整代码块排版及样式"
      ],
      "refactor": ["归纳图标样式至 main.css 统一管理"]
    }
  },
  "1.9.3": {
    "date": "2026-06-20",
    "changes": {
      "feature": ["新增 Giscus 评论系统集中配置，统一管理 repo 和类别信息"],
      "fix": ["恢复旧版网页链接新标签页打开行为"],
      "improve": [
        "优化服务器信息组件排版及样式（新增城市图标、调整版本号位置）",
        "朱雀仿宋字体优先回落至霞鹜新晰宋，提升字体渲染兼容性"
      ],
      "chore": ["改用 Vite 环境变量管理 API 密钥和地址，增强安全性"]
    }
  },
  "1.9.2": {
    "date": "2026-06-20",
    "changes": {
      "improve": ["更新字体引入方式，优化加载性能"],
      "refactor": ["优化 Markdown 渲染样式和结构，增强可读性"]
    }
  },
  "1.9.1": {
    "date": "2026-06-19",
    "changes": {
      "feature": [
        "新增 Test.vue 测试视图，便于测试各种组件和功能（仅用于开发环境）",
        "实现 Markdown 渲染动态（朋友圈）和评论功能"
      ],
      "fix": [
        "修复 1.9.0 版本中设置错误的 CSS 样式问题",
        "恢复 1.9.0 版本中丢失的环境配置、素材和存档页"
      ]
    }
  },
  "1.9.0": {
    "date": "2026-06-18",
    "changes": {
      "feature": ["ServerInfo 组件新增剪贴板粘贴功能，便于输入服务器地址"],
      "refactor": [
        "重构 localStorage 存储架构，采用三级分组存储（GLOBAL_INFO / READER_SETTINGS / READING_STATE）",
        "统一读取和设置函数，优化键名映射与兼容性获取",
        "新增存储迁移逻辑，支持全局信息、阅读器设置和阅读状态的旧数据自动迁移",
        "简化数据迁移过程，移除冗余的旧键名处理逻辑"
      ],
      "improve": [
        "升级 daisyui 至 5.5.23",
        "增强章节内容缓存管理，提升离线阅读体验",
        "更新滚动到上次阅读位置的实现，增强稳定性",
        "优化字体定义、警告框（Alert）和代码块（CodeBlock）样式，增强可读性和布局一致性",
        "优化变更日志中标签的样式，调整颜色类以提升视觉一致性",
        "调整导航栏（NavBar）响应式显示",
        "优化服务器信息组件（ServerInfo）样式和功能",
        "增强更新通知功能",
        "优化更新日志和变更详情的样式，增强可读性"
      ],
      "fix": [
        "修复主题存储逻辑，确保主题值正确访问",
        "修复迁移逻辑，启用旧键名清理功能以确保数据整洁"
      ]
    },
    "note": "本次更新重构了 localStorage 存储架构，旧数据会自动迁移至新结构，不影响正常使用。"
  },
  "1.8.4": {
    "date": "2026-02-16",
    "changes": {
      "fix": ["服务器状态信息接口地址失效的问题"]
    }
  },
  "1.8.3": {
    "date": "2025-11-04",
    "changes": {
      "improve": ["调整章节信息格式，新增修改日期显示"]
    }
  },
  "1.8.2": {
    "date": "2025-10-28",
    "changes": {
      "improve": ["更改获取章节目录的位置"]
    }
  },
  "1.8.1": {
    "date": "2025-08-17",
    "changes": {
      "improve": [
        "更新阅读进度判断逻辑，精确至段落级别",
        "微调更新提示和段落评论按钮的样式",
        "统一更新日志变量命名，优化样式展示",
        "优化点击限制逻辑，提升交互体验"
      ],
      "refactor": ["抽取更新详情组件，简化更新提醒代码"],
      "performance": ["增加新的无效 Storage 键值至清理列表"]
    },
    "note": "本次更新包含存储清理优化，不影响正常使用。"
  },
  "1.8.0": {
    "date": "2025-08-17",
    "changes": {
      "feature": ["阅读器新增段落评论功能，优化内容展示与交互体验"],
      "fix": ["Modal 组件开启关闭无动画的问题"],
      "refactor": [
        "重构更新日志数据结构",
        "使用通用全局事件监听器替代段落评论中原有事件处理逻辑"
      ]
    }
  },
  "1.7.1": {
    "date": "2025-07-05",
    "changes": {
      "feature": ["新增每日一句 API 接口", "实现彩蛋功能，支持动态问候语更新"],
      "improve": [
        "优化 Markdown 组件细节样式",
        "改进 UpdateDetail 组件版本信息展示",
        "优化 Changelog 组件间距和排版"
      ],
      "fix": ["Modal 组件 description 属性类型警告"]
    },
    "note": "本次更新将清除废弃数据，不影响使用。"
  },
  "1.7.0": {
    "date": "2025-07-03",
    "changes": {
      "feature": ["新增代码块复制功能"],
      "refactor": ["重构 Changelog 组件采用时间线布局"],
      "improve": [
        "优化 Markdown 锚点交互设计",
        "独立 Markdown 自定义插件系统，提升可维护性"
      ],
      "performance": [
        "规范 useHeadingTracker 修改路由方式",
        "优化脚注渲染逻辑与链接样式"
      ]
    }
  },
  "1.6.5": {
    "date": "2025-07-02",
    "changes": {
      "fix": ["容器被意外分割的问题，增强代码块和自定义容器的分页处理"],
      "performance": [
        "优化 splitMarkdown 分页逻辑，增加标题悬挂检测，防止标题单独出现在页尾",
        "引入视觉长度计算算法，优化分页准确性"
      ]
    }
  },
  "1.6.4": {
    "date": "2025-07-02",
    "changes": {
      "improve": [
        "改进 Markdown 渲染后的聊天界面视觉表现，优化响应式设计（图标/文字/头像）"
      ],
      "performance": ["优化『已继续上次阅读』提示的触发逻辑"]
    }
  },
  "1.6.3": {
    "date": "2025-07-02",
    "changes": {
      "improve": ["标题更新时机，确保首标题可见后才记录进度"],
      "fix": ["标题跟随失效问题，优化跳转流畅度"],
      "refactor": ["标题跟踪逻辑，采用手动哈希变化标识，移除实验性滚动功能"],
      "performance": ["调整标题检测偏移量，提升定位准确性"]
    }
  },
  "1.6.2": {
    "date": "2025-07-02",
    "changes": {
      "improve": ["调整底部导航栏样式，优化更新日志链接位置"],
      "fix": ["ServerInfo 组件在亮色主题下的配色问题"],
      "performance": ["全面采用 WEBP 图片格式，提升加载性能"]
    }
  },
  "1.6.1": {
    "date": "2025-07-02",
    "changes": {
      "feature": ["新增 Markdown 自定义容器：聊天气泡样式支持"],
      "improve": ["独立 Markdown 组件的 alertPlugin 插件，提升可维护性"]
    }
  },
  "1.6.0": {
    "date": "2025-07-01",
    "changes": {
      "feature": [
        "新增 useServerApi 函数实现服务器信息获取",
        "新增 useHeadingTracker 组件实现阅读位置跟踪",
        "新增 scrollToHash 工具函数支持精准页面跳转",
        "新增 ServerInfo 组件展示服务器状态",
        "Markdown 渲染新增 markdown-it-abbr/emoji/sub/sup 扩展支持"
      ],
      "improve": [
        "重命名 useCleanOldStorage 为 useDiscardStorage 提高可读性",
        "优化 Loading 组件支持动态尺寸调整"
      ],
      "fix": ["更新日志与阅读器样式冲突问题"],
      "performance": [
        "分离 splitMarkdown 函数，优化章节内容加载逻辑",
        "优化 Modal 组件插槽机制防御 XSS 攻击",
        "优化存储清理逻辑和预渲染"
      ]
    }
  },
  "1.5.1": {
    "date": "2025-05-20",
    "changes": {
      "performance": [
        "新增 @vscode/markdown-it-katex 和 markdown-it-container 依赖",
        "升级 katex 版本，移除旧版 markdown-it-katex",
        "优化 Markdown 渲染和分页逻辑，调整段落高度配置"
      ]
    }
  },
  "1.5.0": {
    "date": "2025-05-19",
    "changes": {
      "feature": ["新增 Markdown 渲染插件支持，优化 vue-markdown 组件配置"],
      "improve": [
        "优化 Reader 组件样式，增强文本排版和脚注显示效果",
        "优化 Toast 组件样式",
        "简化相关命名"
      ]
    }
  },
  "1.4.1": {
    "date": "2025-04-29",
    "changes": {
      "improve": [
        "优化设置已读章节的逻辑",
        "解耦数据依赖，使 Markdown 组件更加通用",
        "调整样式",
        "规范组件存放位置"
      ],
      "performance": ["优化小说阅读器检查监听路由参数逻辑"]
    }
  },
  "1.4.0": {
    "date": "2025-04-25",
    "changes": {
      "feature": [
        "新增按钮防重复点击功能",
        "集成新的时间格式化工具",
        "增强阅读器状态管理能力"
      ],
      "improve": ["精简组件 props，移除冗余属性", "优化页码显示样式"],
      "fix": ["章节切换首章失效问题", "Toast 样式失效问题"],
      "performance": [
        "抽象 type-changelog 工具函数，提升复用性",
        "改进网页标题更新逻辑"
      ]
    }
  },
  "1.3.3": {
    "date": "2025-04-24",
    "changes": {
      "improve": [
        "更新日志页面样式细节调整",
        "进一步规范文件存放结构和命名规则"
      ],
      "performance": ["优化阅读器样式控制器实现"]
    }
  },
  "1.3.2": {
    "date": "2025-04-24",
    "changes": {
      "improve": [
        "微调全局样式细节",
        "优化 Toast 组件的样式配置",
        "全面优化代码注释质量",
        "规范文件存放结构，更新引用路径",
        "更新项目结构说明文档"
      ]
    },
    "note": "文件路径调整可能影响自定义引用，建议检查相关配置"
  },
  "1.3.1": {
    "date": "2025-04-24",
    "changes": {
      "refactor": [
        "重构 Toast 方法，简化调用方式，降低使用成本",
        "重构 Modal 方法，简化调用方式，降低使用成本"
      ],
      "performance": ["全面规范化命名，修正路径引用"]
    }
  },
  "1.3.0": {
    "date": "2025-04-23",
    "changes": {
      "feature": ["新增 Toast 功能，实现次要通知"],
      "improve": [
        "模块化 novelStore，提升代码维护性",
        "更新日志页增加回到顶部按钮",
        "精简 showMsg 方法，去除分散组件，增强维护性",
        "优化样式显示"
      ],
      "performance": ["简化代码，去除多余引用"]
    }
  },
  "1.2.5": {
    "date": "2025-04-20",
    "changes": {
      "feature": ["增加强制清理废弃数据功能"],
      "fix": ["阅读器样式菜单函数传入错误的问题"]
    },
    "note": "今后更新默认清除废弃数据，不再提示。"
  },
  "1.2.4": {
    "date": "2025-04-20",
    "changes": {
      "feature": ["补充添加遗漏的路由配置"],
      "improve": ["添加更新日志入口", "调整应清除的遗弃数据范围"]
    },
    "note": "本次更新将清除废弃数据，不影响使用。"
  },
  "1.2.3": {
    "date": "2025-04-20",
    "changes": {
      "feature": ["新增版本更新日志"],
      "improve": [
        "修改 ChapterInfo 组件样式，规范化 HTML 语法结构",
        "分离阅读器样式与小说状态管理逻辑",
        "精简 Modal 对话框组件的调用方式"
      ]
    },
    "note": "本次更新将清除废弃数据，不影响使用。"
  },
  "1.2.2": {
    "date": "2025-04-16",
    "changes": {
      "improve": ["二维码在暗色主题下的显示，统一排版与对话框组件样式"],
      "fix": ["最近更新章节判断逻辑错误"],
      "performance": ["精简章节内容缓存机制，去除多余模块和注释"]
    }
  },
  "1.2.1": {
    "date": "2025-04-14",
    "changes": {
      "improve": ["显示效果，提升阅读体验"],
      "fix": ["章节目录缓存读取问题"]
    }
  },
  "1.2.0": {
    "date": "2025-04-14",
    "changes": {
      "feature": [
        "新增 front-matter 模块支持",
        "新增大版本更新清除遗弃缓存功能"
      ],
      "performance": ["优化章节逻辑以适应新版目录结构，提升 Modal 组件性能"]
    },
    "warning": "此次更新将清除以往的阅读记录。"
  },
  "1.1.2": {
    "date": "2025-04-14",
    "changes": {
      "improve": ["抽象滚动逻辑，分离页面布局与逻辑"],
      "fix": ["刷新当前章节内容失效的问题", "页面切换逻辑"]
    }
  },
  "1.1.1": {
    "date": "2025-04-13",
    "changes": {
      "improve": [
        "抽象章节监听、标题更新、图片加载状态管理逻辑",
        "进一步拆分页面布局逻辑"
      ]
    }
  },
  "1.1.0": {
    "date": "2025-04-13",
    "changes": {
      "feature": [
        "新增 Modal 组件，实现模态对话框提示",
        "新增清除阅读记录功能",
        "章节为最新时弹出提示对话框"
      ],
      "improve": ["图片加载骨架屏效果"],
      "fix": ["NumberController 的值范围判断逻辑"]
    }
  },
  "1.0.0": {
    "date": "2025-03-06",
    "changes": {
      "refactor": ["使用 Vue3 + Vite 构建的全新网页"]
    }
  }
}
